pyclack/__init__.py
pyclack/core/__init__.py
pyclack/core/confirm.py
pyclack/core/multiselect.py
pyclack/core/password.py
pyclack/core/prompt.py
pyclack/core/select.py
pyclack/core/select_key.py
pyclack/core/spinner.py
pyclack/core/text.py
pyclack/prompts/__init__.py
pyclack/prompts/confirm.py
pyclack/prompts/mutliselect.py
pyclack/prompts/password.py
pyclack/prompts/select.py
pyclack/prompts/spinner.py
pyclack/prompts/text.py
pyclack/utils/__init__.py
pyclack/utils/styling.py
pyclack_cli-0.4.0.dist-info/METADATA
pyclack_cli-0.4.0.dist-info/WHEEL
pyclack_cli-0.4.0.dist-info/top_level.txt
pyclack_cli-0.4.0.dist-info/RECORD
