Metadata-Version: 2.1
Name: pyclack-cli
Version: 0.4.0
Summary: A python library for building interactive command line interfaces effortlessly. Inspired by clack.cc
Home-page: https://github.com/Bbalduzz/pyclack
Author: Edoardo Balducci
Author-email: edoardoba2004@gmail.com
Classifier: Programming Language :: Python :: 3
Classifier: License :: OSI Approved :: MIT License
Classifier: Operating System :: OS Independent
Requires-Python: >=3.7
Requires-Dist: readchar
Provides-Extra: core
Requires-Dist: readchar; extra == "core"
Provides-Extra: prompts
Requires-Dist: readchar; extra == "prompts"
Provides-Extra: all
Requires-Dist: readchar; extra == "all"
